XuexiIonicShiyongIonicGoujianShishiHunheYidongYingyongChugao/README.md
XuexiIonicShiyongIonicGoujianShishiHunheYidongYingyongChugao/__init__.py
XuexiIonicShiyongIonicGoujianShishiHunheYidongYingyongChugao/__main__.py
XuexiIonicShiyongIonicGoujianShishiHunheYidongYingyongChugao/file.epub
XuexiIonicShiyongIonicGoujianShishiHunheYidongYingyongChugao/index.html
XuexiIonicShiyongIonicGoujianShishiHunheYidongYingyongChugao/css/__init__.py
XuexiIonicShiyongIonicGoujianShishiHunheYidongYingyongChugao/css/annotations.css
XuexiIonicShiyongIonicGoujianShishiHunheYidongYingyongChugao/css/main.css
XuexiIonicShiyongIonicGoujianShishiHunheYidongYingyongChugao/css/normalize.css
XuexiIonicShiyongIonicGoujianShishiHunheYidongYingyongChugao/css/popup.css
XuexiIonicShiyongIonicGoujianShishiHunheYidongYingyongChugao/font/__init__.py
XuexiIonicShiyongIonicGoujianShishiHunheYidongYingyongChugao/font/fontello.eot
XuexiIonicShiyongIonicGoujianShishiHunheYidongYingyongChugao/font/fontello.svg
XuexiIonicShiyongIonicGoujianShishiHunheYidongYingyongChugao/font/fontello.ttf
XuexiIonicShiyongIonicGoujianShishiHunheYidongYingyongChugao/font/fontello.woff
XuexiIonicShiyongIonicGoujianShishiHunheYidongYingyongChugao/img/__init__.py
XuexiIonicShiyongIonicGoujianShishiHunheYidongYingyongChugao/img/annotator-glyph-sprite.png
XuexiIonicShiyongIonicGoujianShishiHunheYidongYingyongChugao/img/annotator-icon-sprite.png
XuexiIonicShiyongIonicGoujianShishiHunheYidongYingyongChugao/img/apple-touch-icon.png
XuexiIonicShiyongIonicGoujianShishiHunheYidongYingyongChugao/img/cancelfullscreen.png
XuexiIonicShiyongIonicGoujianShishiHunheYidongYingyongChugao/img/close.png
XuexiIonicShiyongIonicGoujianShishiHunheYidongYingyongChugao/img/fullscreen.png
XuexiIonicShiyongIonicGoujianShishiHunheYidongYingyongChugao/img/loader.gif
XuexiIonicShiyongIonicGoujianShishiHunheYidongYingyongChugao/img/menu-icon.png
XuexiIonicShiyongIonicGoujianShishiHunheYidongYingyongChugao/img/save.png
xuexi_ionic_shiyong_ionic_goujian_shishi_hunhe_yidong_yingyong_chugao-2024.3.2.0.dist-info/METADATA
xuexi_ionic_shiyong_ionic_goujian_shishi_hunhe_yidong_yingyong_chugao-2024.3.2.0.dist-info/WHEEL
xuexi_ionic_shiyong_ionic_goujian_shishi_hunhe_yidong_yingyong_chugao-2024.3.2.0.dist-info/entry_points.txt
xuexi_ionic_shiyong_ionic_goujian_shishi_hunhe_yidong_yingyong_chugao-2024.3.2.0.dist-info/top_level.txt
xuexi_ionic_shiyong_ionic_goujian_shishi_hunhe_yidong_yingyong_chugao-2024.3.2.0.dist-info/RECORD
