Metadata-Version: 2.1
Name: xuexi-ionic-shiyong-ionic-goujian-shishi-hunhe-yidong-yingyong-chugao
Version: 2024.3.2.0
Summary: 学习Ionic - 使用Ionic构建实时混合移动应用（初稿）
Home-page: https://github.com/apachecn/xuexi-ionic-shiyong-ionic-goujian-shishi-hunhe-yidong-yingyong-chugao
Author: ApacheCN
Author-email: apachecn@163.com
Classifier: Development Status :: 4 - Beta
Classifier: Environment :: Console
Classifier: Intended Audience :: Developers
Classifier: Intended Audience :: End Users/Desktop
Classifier: License :: Other/Proprietary License
Classifier: Natural Language :: Chinese (Simplified)
Classifier: Natural Language :: English
Classifier: Operating System :: OS Independent
Classifier: Programming Language :: Python :: 3
Classifier: Programming Language :: Python :: 3 :: Only
Classifier: Programming Language :: Python :: 3.6
Classifier: Programming Language :: Python :: 3.7
Classifier: Topic :: Text Processing :: Markup :: Markdown
Classifier: Topic :: Text Processing :: Markup :: HTML
Classifier: Topic :: Internet :: WWW/HTTP
Classifier: Topic :: Software Development :: Documentation
Classifier: Topic :: Documentation
Requires-Python: >=3.6
